aerie/__init__.py
aerie/base.py
aerie/collections.py
aerie/database.py
aerie/exceptions.py
aerie/models.py
aerie/paginator.py
aerie/queries.py
aerie/results.py
aerie/schema.py
aerie/session.py
aerie/utils.py
aerie-0.8.2.dist-info/LICENSE
aerie-0.8.2.dist-info/WHEEL
aerie-0.8.2.dist-info/METADATA
aerie-0.8.2.dist-info/RECORD
