Metadata-Version: 2.1
Name: aerie
Version: 0.8.2
Summary: An async database toolkit.
Home-page: https://github.com/alex-oleshkevich/aerie
License: MIT
Author: Alex Oleshkevich
Author-email: alex.oleshkevich@gmail.com
Requires-Python: >=3.9.0,<4.0.0
Classifier: Development Status :: 5 - Production/Stable
Classifier: Environment :: Web Environment
Classifier: Intended Audience :: Developers
Classifier: License :: OSI Approved :: MIT License
Classifier: Operating System :: OS Independent
Classifier: Programming Language :: Python :: 3
Classifier: Programming Language :: Python :: 3.10
Classifier: Programming Language :: Python :: 3.9
Classifier: Topic :: Software Development :: Libraries :: Python Modules
Classifier: Typing :: Typed
Provides-Extra: full
Provides-Extra: postgresql
Provides-Extra: sqlite
Requires-Dist: SQLAlchemy[asyncio] (>=1.4.27,<2.0.0)
Requires-Dist: aiosqlite (>=0.17.0,<0.18.0); extra == "sqlite" or extra == "full"
Requires-Dist: asyncpg (>=0.25.0,<0.26.0); extra == "postgresql" or extra == "full"
Project-URL: Documentation, https://github.com/alex-oleshkevich/aerie
Project-URL: Repository, https://github.com/alex-oleshkevich/aerie
